mtcli/__init__.py
mtcli/commands/__init__.py
mtcli/commands/bars.py
mtcli/commands/conf.py
mtcli/commands/logs.py
mtcli/conecta.py
mtcli/conf.py
mtcli/data/__init__.py
mtcli/data/base.py
mtcli/data/csv.py
mtcli/data/mt5.py
mtcli/logger.py
mtcli/models/__init__.py
mtcli/models/bar_model.py
mtcli/models/bars_model.py
mtcli/models/chart_model.py
mtcli/models/conf_model.py
mtcli/models/consecutive_bars_model.py
mtcli/models/rates_model.py
mtcli/models/signals_model.py
mtcli/models/unconsecutive_bar_model.py
mtcli/mt.py
mtcli/mt5_context.py
mtcli/plugin.py
mtcli/plugins/__init__.py
mtcli/plugins/media_movel/__init__.py
mtcli/plugins/media_movel/command.py
mtcli/plugins/media_movel/conf.py
mtcli/plugins/media_movel/models/__init__.py
mtcli/plugins/media_movel/models/model_media_movel.py
mtcli/plugins/media_movel/tests/__init__.py
mtcli/plugins/media_movel/tests/test_mm.py
mtcli/plugins/media_movel/tests/test_model_media_movel.py
mtcli/plugins/range_medio/__init__.py
mtcli/plugins/range_medio/command.py
mtcli/plugins/range_medio/conf.py
mtcli/plugins/range_medio/models/__init__.py
mtcli/plugins/range_medio/models/average_range_model.py
mtcli/plugins/range_medio/tests/__init__.py
mtcli/plugins/range_medio/tests/test_rm.py
mtcli/plugins/volume_medio/__init__.py
mtcli/plugins/volume_medio/command.py
mtcli/plugins/volume_medio/conf.py
mtcli/plugins/volume_medio/models/__init__.py
mtcli/plugins/volume_medio/models/model_average_volume.py
mtcli/plugins/volume_medio/tests/__init__.py
mtcli/plugins/volume_medio/tests/test_vm.py
mtcli/views/__init__.py
mtcli/views/close_view.py
mtcli/views/full_view.py
mtcli/views/high_view.py
mtcli/views/low_view.py
mtcli/views/min_view.py
mtcli/views/open_view.py
mtcli/views/ranges_view.py
mtcli/views/rates_view.py
mtcli/views/vars_view.py
mtcli/views/volumes_view.py
mtcli-3.4.0.dist-info/entry_points.txt
mtcli-3.4.0.dist-info/LICENSE
mtcli-3.4.0.dist-info/METADATA
mtcli-3.4.0.dist-info/WHEEL
mtcli-3.4.0.dist-info/RECORD
