Metadata-Version: 2.3
Name: mtcli
Version: 3.4.0
Summary: Aplicativo CLI para exibir gráficos do MetaTrader 5 em texto acessível ao leitor de telas
License: GPL-3.0
Keywords: MetaTrader 5,trading,CLI
Author: Valmir França da Silva
Author-email: vfranca3@gmail.com
Requires-Python: >=3.10,<3.14.0
Classifier: License :: OSI Approved :: GNU General Public License v3 (GPLv3)
Classifier: Programming Language :: Python :: 3
Classifier: Programming Language :: Python :: 3.10
Classifier: Programming Language :: Python :: 3.11
Classifier: Programming Language :: Python :: 3.12
Classifier: Programming Language :: Python :: 3.13
Requires-Dist: click (>=8.2.1,<9.0.0)
Requires-Dist: metatrader5 (>=5.0.5260,<6.0.0)
Project-URL: Documentation, https://mtcli.readthedocs.io/pt-br/latest
Project-URL: Homepage, https://pypi.org/project/mtcli
Project-URL: Repository, https://github.com/vfranca/mtcli
Project-URL: issues, https://github.com/vfranca/mtcli/issues
